jinja2_sanic/__init__.py
jinja2_sanic-0.1.2.dist-info/DESCRIPTION.rst
jinja2_sanic-0.1.2.dist-info/METADATA
jinja2_sanic-0.1.2.dist-info/RECORD
jinja2_sanic-0.1.2.dist-info/WHEEL
jinja2_sanic-0.1.2.dist-info/metadata.json
jinja2_sanic-0.1.2.dist-info/top_level.txt
tests/__init__.py
tests/conftest.py
tests/test_context_processors.py
tests/test_jinja_filters.py
tests/test_jinja_globals.py
tests/test_render.py
